{
  "sport": {
    "id": "289u5typ3vp4ifwh5thalohmq",
    "name": "Soccer"
  },
  "ruleset": {
    "id": "79plas4983031idr6vw83nuel",
    "name": "Men"
  },
  "competition": {
    "id": "722fdbecxzcq9788l6jqclzlw",
    "name": "2. Bundesliga"
  },
  "tournamentCalendar": {
    "id": "7u6i088r32wrl84442qxr0gh6",
    "startDate": "2020-09-18Z",
    "endDate": "2021-05-23Z",
    "name": "2020/2021"
  },
  "stage":[
    {
      "id": "6tca7sbnh37w596ws64rrez8p",
      "formatId": "e2q01r9o9jwiq1fls93d1sslx",
      "startDate": "2020-09-18Z",
      "endDate": "2021-05-23Z",
      "name": "Regular Season",
      "division": [
        {
          "type": "total",
          "ranking": [
            {
              "id": "rank-id-0000000000001",
              "rank": 1,
              "rankStatus": "Promotion",
              "contestantId": "9dlxuym0eab00j9ggrdr87soj",
              "contestantName": "Greuther Fürth",
              "contestantShortName": "Greuther Fürth",
              "contestantClubName": "SpVgg Greuther Fürth",
              "contestantCode": "SGF",
              "points": 18,
              "matchesPlayed": 9,
              "matchesWon":  5,
              "matchesLost":  1,
              "matchesDrawn": 3,
              "goalsFor": 19,
              "goalsAgainst": 10,
              "goalDifference": "+9",
              "lastSix": "WWWWW"
            },
            {
              "id": "rank-id-0000000000002",
              "rank": 2,
              "rankStatus": "Promotion",
              "contestantId": "eq1oq6y61xnzq88zu0cnw131z",
              "contestantName": "Bochum",
              "contestantShortName": "Bochum",
              "contestantClubName": "VfL Bochum 1848",
              "contestantCode": "BOC",
              "points": 17,
              "matchesPlayed": 9,
              "matchesWon": 5,
              "matchesLost": 2,
              "matchesDrawn": 3,
              "goalsFor": 17,
              "goalsAgainst": 9,
              "goalDifference": "+8",
              "lastSix": "WWLWW"
            },
            {
              "id": "rank-id-0000000000003",
              "rank": 3,
              "rankStatus": "Promotion",
              "contestantId": "75xi6hloabmnjn2kzgj1g8h1s",
              "contestantName": "Hamburger SV",
              "contestantShortName": "Hamburg",
              "contestantClubName": "Hamburger SV",
              "contestantCode": "HSV",
              "points": 17,
              "matchesPlayed": 9,
              "matchesWon": 5,
              "matchesLost": 2,
              "matchesDrawn": 2,
              "goalsFor": 19,
              "goalsAgainst": 14,
              "goalDifference": "+5",
              "lastSix": "WDDLL"
            },
            {
              "id": "rank-id-0000000000004",
              "rank": 4,
              "rankStatus": "Relegation",
              "contestantId": "6zwg0wxjie31da2i4wwh2h4ho",
              "contestantName": "Holstein Kiel",
              "contestantShortName": "Holstein",
              "contestantClubName": "Kieler SV Holstein 1900",
              "contestantCode": "KSV",
              "points": 16,
              "matchesPlayed": 9,
              "matchesWon": 4,
              "matchesLost": 1,
              "matchesDrawn": 4,
              "goalsFor": 13,
              "goalsAgainst": 8,
              "goalDifference": "+5",
              "lastSix": "LDDDW"
            },
            {
              "id": "rank-id-0000000000005",
              "rank": 5,
              "rankStatus": "Promotion",
              "contestantId": "tmbl2xxxxxxxxxxxxxxxx01",
              "contestantName": "VfL Osnabrück",
              "contestantShortName": "Osnabrück",
              "contestantClubName": "VfL Osnabrück",
              "contestantCode": "OSN",
              "points": 16,
              "matchesPlayed": 9,
              "matchesWon": 4,
              "matchesLost": 1,
              "matchesDrawn": 4,
              "goalsFor": 13,
              "goalsAgainst": 11,
              "goalDifference": "+2",
              "lastSix": "DWWLW"
            },
            {
              "id": "rank-id-0000000000006",
              "rank": 6,
              "rankStatus": "Relegation",
              "contestantId": "m5tpogrj0txk7qjdbb57wba",
              "contestantName": "Erzgebirge Aue",
              "contestantShortName": "Aue",
              "contestantClubName": "FC Erzgebirge Aue",
              "contestantCode": "AUE",
              "points": 15,
              "matchesPlayed": 9,
              "matchesWon": 4,
              "matchesLost": 2,
              "matchesDrawn": 3,
              "goalsFor": 14,
              "goalsAgainst": 9,
              "goalDifference": "+5",
              "lastSix": "LDDWW"
            },
            {
              "id": "rank-id-0000000000007",
              "rank": 7,
              "rankStatus": "Relegation",
              "contestantId": "62ljqd4za2a6svd9wgctg8b53",
              "contestantName": "Paderborn",
              "contestantShortName": "Paderborn",
              "contestantClubName": "SC Paderborn 07",
              "contestantCode": "PAD",
              "points": 14,
              "matchesPlayed": 9,
              "matchesWon": 4,
              "matchesLost": 3,
              "matchesDrawn": 2,
              "goalsFor": 14,
              "goalsAgainst": 8,
              "goalDifference": "+6",
              "lastSix": "DWWWL"
            },
            {
              "id": "rank-id-0000000000008",
              "rank": 8,
              "rankStatus": "Promotion",
              "contestantId": "tmbl2xxxxxxxxxxxxxxxx04",
              "contestantName": "Karlsruher SC",
              "contestantShortName": "Karlsruher SC",
              "contestantClubName": "Karlsruher SC",
              "contestantCode": "KAR",
              "points":13 ,
              "matchesPlayed": 9,
              "matchesWon": 4,
              "matchesLost": 4,
              "matchesDrawn": 1,
              "goalsFor": 14,
              "goalsAgainst": 10,
              "goalDifference": "+4",
              "lastSix": "DLWWW"
            },
            {
              "id": "rank-id-0000000000009",
              "rank": 9,
              "rankStatus": "Relegation",
              "contestantId": "3xcg7xikgrn2x8oa65sopb2is",
              "contestantName": "Heidenheim",
              "contestantShortName": "Heidenheim",
              "contestantClubName": "1. FC Heidenheim 1846",
              "contestantCode": "HDH",
              "points": 12,
              "matchesPlayed": 9,
              "matchesWon": 3,
              "matchesLost": 3,
              "matchesDrawn": 3,
              "goalsFor": 15,
              "goalsAgainst": 13,
              "goalDifference": "+2",
              "lastSix": "DLWDL"
            },
            {
              "id": "rank-id-0000000000010",
              "rank": 10,
              "rankStatus": "Promotion",
              "contestantId": "d4p104ikzzt5hfwdzppbmp7e0",
              "contestantName": "Jahn Regensburg",
              "contestantShortName": "Regensburg",
              "contestantClubName": "SSV Jahn 2000 Regensburg",
              "contestantCode": "REG",
              "points": 12,
              "matchesPlayed": 9,
              "matchesWon": 3,
              "matchesLost": 3,
              "matchesDrawn": 3,
              "goalsFor": 13,
              "goalsAgainst": 14,
              "goalDifference": "-1",
              "lastSix": "WLLLW"
            },
            {
              "id": "rank-id-0000000000011",
              "rank": 11,
              "rankStatus": "Promotion",
              "contestantId": "1y7e48j8swyafegsucvewse5a",
              "contestantName": "Darmstadt 98",
              "contestantShortName": "Darmstadt 98",
              "contestantClubName": "SV Darmstadt 1898",
              "contestantCode": "D98",
              "points": 12,
              "matchesPlayed": 9,
              "matchesWon": 3,
              "matchesLost": 3,
              "matchesDrawn": 3,
              "goalsFor": 16,
              "goalsAgainst": 18,
              "goalDifference": "-2",
              "lastSix": "DWLLW"
            },
            {
              "id": "rank-id-0000000000012",
              "rank": 12,
              "rankStatus": "Relegation",
              "contestantId": "tmbl2xxxxxxxxxxxxxxxx02",
              "contestantName": "Fortuna Dusseldorf",
              "contestantShortName": "Fortuna Dusseldorf",
              "contestantClubName": "Fortuna Dusseldorf",
              "contestantCode": "FDS",
              "points": 11,
              "matchesPlayed": 9,
              "matchesWon": 3,
              "matchesLost": 4,
              "matchesDrawn": 2,
              "goalsFor": 8,
              "goalsAgainst": 15,
              "goalDifference": "-7",
              "lastSix": "LWDWL"
            },
            {
              "id": "rank-id-0000000000013",
              "rank": 13,
              "rankStatus": "Relegation",
              "contestantId": "tmbl2xxxxxxxxxxxxxxxx05",
              "contestantName": "Nuremberg",
              "contestantShortName": "Nuremberg",
              "contestantClubName": "1. FC Nuremberg",
              "contestantCode": "NUR",
              "points": 10,
              "matchesPlayed": 9,
              "matchesWon": 2,
              "matchesLost": 3,
              "matchesDrawn": 4,
              "goalsFor": 16,
              "goalsAgainst": 15,
              "goalDifference": "+1",
              "lastSix": "DLDWL"
            },
            {
              "id": "rank-id-0000000000014",
              "rank": 14,
              "rankStatus": "Relegation",
              "contestantId": "tmbl2xxxxxxxxxxxxxxxx06",
              "contestantName": "Hanover",
              "contestantShortName": "Hanover",
              "contestantClubName": "Hanover 96",
              "contestantCode": "H96",
              "points": 10,
              "matchesPlayed": 9,
              "matchesWon": 3,
              "matchesLost": 5,
              "matchesDrawn": 1,
              "goalsFor": 12,
              "goalsAgainst": 13,
              "goalDifference": "-1",
              "lastSix": "WLDLL"
            },
            {
              "id": "rank-id-0000000000015",
              "rank": 15,
              "rankStatus": "Relegation",
              "contestantId": "884uzyf1wosc7ykji6e18gifp",
              "contestantName": "Sandhausen",
              "contestantShortName": "Sandhausen",
              "contestantClubName": "SV Sandhausen",
              "contestantCode": "SVS",
              "points": 8,
              "matchesPlayed": 9,
              "matchesWon": 2,
              "matchesLost": 5,
              "matchesDrawn": 2,
              "goalsFor": 9,
              "goalsAgainst": 16,
              "goalDifference": "-7",
              "lastSix": "DLDLL"
            },
            {
              "id": "rank-id-0000000000016",
              "rank": 16,
              "rankStatus": "Promotion",
              "contestantId": "tmbl2xxxxxxxxxxxxxxxx03",
              "contestantName": "Eintracht Braunschwig",
              "contestantShortName": "Eintracht Braunschwig",
              "contestantClubName": "Eintracht Braunschwig",
              "contestantCode": "EBR",
              "points": 8,
              "matchesPlayed": 9,
              "matchesWon": 2,
              "matchesLost": 5,
              "matchesDrawn": 2,
              "goalsFor": 9,
              "goalsAgainst": 21,
              "goalDifference": "-12",
              "lastSix": "LWDLL"
            },
            {
              "id": "rank-id-0000000000017",
              "rank": 17,
              "rankStatus": "Relegation",
              "contestantId": "85jtaw5dcxxx1yp8te6axh3p8",
              "contestantName": "St. Pauli",
              "contestantShortName": "St. Pauli",
              "contestantClubName": "FC St. Pauli",
              "contestantCode": "STP",
              "points": 7,
              "matchesPlayed": 9,
              "matchesWon": 1,
              "matchesLost": 4,
              "matchesDrawn": 4,
              "goalsFor": 12,
              "goalsAgainst": 17,
              "goalDifference": "-5",
              "lastSix": "DDLLL"
            },
            {
              "id": "rank-id-0000000000018",
              "rank": 18,
              "rankStatus": "Relegation",
              "contestantId": "tmbl2xxxxxxxxxxxxxxxx07",
              "contestantName": "Würzburger Kickers",
              "contestantShortName": "Kickers",
              "contestantClubName": "FC Würzburger Kickers",
              "contestantCode": "WUK",
              "points": 4,
              "matchesPlayed": 9,
              "matchesWon": 1,
              "matchesLost": 7,
              "matchesDrawn": 1,
              "goalsFor": 9,
              "goalsAgainst": 21,
              "goalDifference": "-12",
              "lastSix": "LLLWL"
            }
          ]
        }
      ]
    }
  ]
}